stljax/formula.py
stljax/tests.py
stljax/utils.py
stljax/viz.py
stljax-1.1.3.dist-info/licenses/LICENSE
stljax-1.1.3.dist-info/METADATA
stljax-1.1.3.dist-info/WHEEL
stljax-1.1.3.dist-info/top_level.txt
stljax-1.1.3.dist-info/RECORD
