Metadata-Version: 2.4
Name: stljax
Version: 1.1.3
Summary: stlcg with jax
Author: Karen Leung
Author-email: kymleung@uw.edu
License-File: LICENSE
Requires-Dist: jax
Requires-Dist: numpy
Requires-Dist: graphviz
Dynamic: author
Dynamic: author-email
Dynamic: license-file
Dynamic: requires-dist
Dynamic: summary
